django_webpack4_loader-0.0.5.dist-info/DESCRIPTION.rst
django_webpack4_loader-0.0.5.dist-info/METADATA
django_webpack4_loader-0.0.5.dist-info/RECORD
django_webpack4_loader-0.0.5.dist-info/WHEEL
django_webpack4_loader-0.0.5.dist-info/metadata.json
django_webpack4_loader-0.0.5.dist-info/top_level.txt
webpack_loader/__init__.py
webpack_loader/apps.py
webpack_loader/config.py
webpack_loader/errors.py
webpack_loader/exceptions.py
webpack_loader/loader.py
webpack_loader/signals.py
webpack_loader/utils.py
webpack_loader/contrib/__init__.py
webpack_loader/contrib/jinja2ext.py
webpack_loader/templatetags/__init__.py
webpack_loader/templatetags/webpack_loader.py
