Metadata-Version: 2.1
Name: django-webpack4-loader
Version: 0.0.5
Summary: Transparently use webpack with django. Forked from https://github.com/scdekov/django-webpack-loader
Home-page: https://github.com/alihazemfarouk/django-webpack-loader
Author: Ali Farouk
Author-email: alifarouk102@gmail.com
License: UNKNOWN
Keywords: django,webpack,assets
Platform: UNKNOWN
Classifier: Programming Language :: Python :: 3.3
Classifier: Programming Language :: Python :: 3.4
Classifier: Programming Language :: Python :: 3.5
Classifier: Framework :: Django
Classifier: Environment :: Web Environment
Classifier: License :: OSI Approved :: MIT License
